{"chapter":{"chapter_id":38773,"chapter_name":"BNI Doon Sunrisers","region_id":34,"venue_name":"Fairfield by Marriott","address":"Mauza, Malsi, Dehradun, Uttarakhand, Near Max Hospital, Dehradun, Uttarakhand, India, 248001","city":"Mauza","state":"Uttarakhand","latitude":30.3171828,"longitude":78.02786689999999,"meeting_day":"Wednesday","meeting_time":"8:00 AM - 9:30 AM","meeting_schedule":"Meets : Every Wednesday, 8:00 AM - 9:30 AM","total_members":18,"domain":"bni-dehradun.in","detail_url":"chapterdetails.php?chapterId=38773&name=BNI+Doon+Sunrisers&t=cad06f8067f309c934a070b0ca8ac8539aed6c29b0bdbb6f74deb94772a00c65","org_type":"CHAPTER","region_name":"dehradun"},"members":[{"member_id":13436,"full_name":"Akhilesh Sharma","profession":"Construction > Cement/Concrete > Cement/Concrete","profession_category":"Construction","company_name":"M.S.Enterprises","city":"Dehradun","chapter_id":38773,"region_id":34,"domain":"bni-dehradun.in"},{"member_id":13437,"full_name":"Anmol Gupta","profession":"Construction > Builder/General Contractor > Builder/General Contractor","profession_category":"Construction","company_name":"B R MEGAINFRA PVT LTD","city":"Dehradun","chapter_id":38773,"region_id":34,"domain":"bni-dehradun.in"},{"member_id":13438,"full_name":"Anup Singh","profession":"Construction > HVAC - Heating & Air > HVAC - Heating & Air","profession_category":"Construction","company_name":"Litmus Solutions","city":"","chapter_id":38773,"region_id":34,"domain":"bni-dehradun.in"},{"member_id":13439,"full_name":"Bharat Singh Patel","profession":"Architecture & Engineering > Architecture & Engineering (Other) > Architect","profession_category":"Architecture & Engineering","company_name":"B Patel Architects","city":"Dehradun","chapter_id":38773,"region_id":34,"domain":"bni-dehradun.in"},{"member_id":13440,"full_name":"Deepak Chaudhary","profession":"Advertising & Marketing > Digital Marketing > Digital Marketing","profession_category":"Advertising & Marketing","company_name":"Creatikartta","city":"Dehradun","chapter_id":38773,"region_id":34,"domain":"bni-dehradun.in"},{"member_id":13441,"full_name":"Gagan Behl","profession":"Legal & Accounting > Accounting Services > Accounting Services","profession_category":"Legal & Accounting","company_name":"Gagan Behl & Co","city":"Dehradun","chapter_id":38773,"region_id":34,"domain":"bni-dehradun.in"},{"member_id":13442,"full_name":"Gagan Goel","profession":"Advertising & Marketing > Printer > Printer","profession_category":"Advertising & Marketing","company_name":"MUTIGRAPHICS PRINT PVT. LTD.","city":"DEHRADUN","chapter_id":38773,"region_id":34,"domain":"bni-dehradun.in"},{"member_id":13443,"full_name":"Jagjeet Singh","profession":"Construction > Construction (Other) > Water Pumps","profession_category":"Construction","company_name":"Supra Electricals","city":"Dehradun","chapter_id":38773,"region_id":34,"domain":"bni-dehradun.in"},{"member_id":13444,"full_name":"Nadimul Islam","profession":"Architecture & Engineering > Civil/structural engineer > Civil/structural engineer","profession_category":"Architecture & Engineering","company_name":"Ehan Construction","city":"DEHRADUN","chapter_id":38773,"region_id":34,"domain":"bni-dehradun.in"},{"member_id":13445,"full_name":"Nitin Mittal","profession":"Construction > Pipework > Pipework","profession_category":"Construction","company_name":"Doon Pipe Store","city":"Dehradun","chapter_id":38773,"region_id":34,"domain":"bni-dehradun.in"},{"member_id":13446,"full_name":"Priya Gulati","profession":"Advertising & Marketing > Branding > Branding","profession_category":"Advertising & Marketing","company_name":"Bagit Consulting Group","city":"Dehradun","chapter_id":38773,"region_id":34,"domain":"bni-dehradun.in"},{"member_id":13447,"full_name":"RAGHAV RAKESH","profession":"Architecture & Engineering > Architect > Architect","profession_category":"Architecture & Engineering","company_name":"Vastushilp Architect and Engineers","city":"Dehradun","chapter_id":38773,"region_id":34,"domain":"bni-dehradun.in"},{"member_id":13448,"full_name":"Rahul Kaushik","profession":"Construction > Kitchen Construction > Kitchen Construction","profession_category":"Construction","company_name":"Earthmax","city":"Dehradun","chapter_id":38773,"region_id":34,"domain":"bni-dehradun.in"},{"member_id":13449,"full_name":"Raj Kiran Jain","profession":"Retail > Retail (Other) > Hospitality Supplier","profession_category":"Retail","company_name":"Hulash Raj Associates","city":"Dehradun,","chapter_id":38773,"region_id":34,"domain":"bni-dehradun.in"},{"member_id":13450,"full_name":"Rashmi Kabra","profession":"Personal Services > Wedding Planner > Wedding Planner","profession_category":"Personal Services","company_name":"Wedbells","city":"Dehradun","chapter_id":38773,"region_id":34,"domain":"bni-dehradun.in"},{"member_id":13451,"full_name":"Tripti Bhanot","profession":"Construction > Interior Design - Commercial > Interior Design - Commercial","profession_category":"Construction","company_name":"T-HOMES DESIGN STUDIO","city":"Dehradun","chapter_id":38773,"region_id":34,"domain":"bni-dehradun.in"},{"member_id":13452,"full_name":"USMAN KHAN","profession":"Manufacturing > Manufacturing (Other) > UPVC DOORS AND WINDOWS","profession_category":"Manufacturing","company_name":"UNIQUE TRADING EST","city":"DEHRADUN","chapter_id":38773,"region_id":34,"domain":"bni-dehradun.in"},{"member_id":13453,"full_name":"Varun Gaind","profession":"Real Estate Services > Real Estate Development > Real Estate Development","profession_category":"Real Estate Services","company_name":"AKG BUILDERS & DEVELOPERS","city":"Dehradun","chapter_id":38773,"region_id":34,"domain":"bni-dehradun.in"}],"professions":[{"profession_category":"Construction","count":7},{"profession_category":"Architecture & Engineering","count":3},{"profession_category":"Advertising & Marketing","count":3},{"profession_category":"Retail","count":1},{"profession_category":"Real Estate Services","count":1},{"profession_category":"Personal Services","count":1},{"profession_category":"Manufacturing","count":1},{"profession_category":"Legal & Accounting","count":1}]}