{"chapter":{"chapter_id":39146,"chapter_name":"Elite","region_id":29,"venue_name":"Merlis Hotel","address":"61, Avinashi Rd, Goldwins, , Karuparampalayam Pirvu, , Coimbatore,, Tamil Nadu , India, 641014","city":"Avinashi Rd","state":"Tamil Nadu","latitude":11.0448561,"longitude":77.0479574,"meeting_day":"Wednesday","meeting_time":"7:30 AM - 9:00 AM","meeting_schedule":"Meets : Every Wednesday, 7:30 AM - 9:00 AM","total_members":25,"domain":"bni-coimbatore.in","detail_url":"chapterdetails.php?chapterId=39146&name=Elite&t=de0f508e9b66e10eefd4a950fb57c0837bee00e59c4d0463aedb70f0071fa90e","org_type":"CHAPTER","region_name":"coimbatore"},"members":[{"member_id":11325,"full_name":"Ajith Kumar Muthuswamy","profession":"Advertising & Marketing > Graphic Designer > Graphic Designer","profession_category":"Advertising & Marketing","company_name":"Addot Branding Agency","city":"Coimbatore","chapter_id":39146,"region_id":29,"domain":"bni-coimbatore.in"},{"member_id":11326,"full_name":"Akash E","profession":"Advertising & Marketing > AI Consultant > AI Consultant","profession_category":"Advertising & Marketing","company_name":"Metarix - Aer Hearing Essentials","city":"Coimbatore,","chapter_id":39146,"region_id":29,"domain":"bni-coimbatore.in"},{"member_id":11327,"full_name":"Alaudin B","profession":"Retail > Retail (Other) > Curtains","profession_category":"Retail","company_name":"Best Decors","city":"Coimbatore","chapter_id":39146,"region_id":29,"domain":"bni-coimbatore.in"},{"member_id":11328,"full_name":"Balaji J","profession":"Finance & Insurance > Life and Disability Insurance > Life and Disability Insurance","profession_category":"Finance & Insurance","company_name":"Tarun Insurance Services","city":"Coimbatore","chapter_id":39146,"region_id":29,"domain":"bni-coimbatore.in"},{"member_id":11329,"full_name":"Balanagamuruga Gunasekaran","profession":"Construction > Solar > Solar","profession_category":"Construction","company_name":"Ryno Trading and Technical service","city":"Coimbatore","chapter_id":39146,"region_id":29,"domain":"bni-coimbatore.in"},{"member_id":11330,"full_name":"Baskaran Pandian","profession":"Real Estate Services > Cleaning Service > Cleaning Service","profession_category":"Real Estate Services","company_name":"Cleaning guru home services","city":"Coimbatore","chapter_id":39146,"region_id":29,"domain":"bni-coimbatore.in"},{"member_id":11331,"full_name":"Hariprasath P.","profession":"Health & Wellness > Hearing/Audiology > Hearing/Audiology","profession_category":"Health & Wellness","company_name":"Isai Hearing Aid Centre","city":"Coimbatore,","chapter_id":39146,"region_id":29,"domain":"bni-coimbatore.in"},{"member_id":11332,"full_name":"Haripriya Binod","profession":"Retail > Retail (Other) > Gemstone and Crystals","profession_category":"Retail","company_name":"Ratna Shala","city":"Coimbatore,","chapter_id":39146,"region_id":29,"domain":"bni-coimbatore.in"},{"member_id":11333,"full_name":"Hema Latha","profession":"Retail > Retail (Other) > Pumps Retailer","profession_category":"Retail","company_name":"Surya Agency","city":"Coimbatore,","chapter_id":39146,"region_id":29,"domain":"bni-coimbatore.in"},{"member_id":11334,"full_name":"Jeeva Thangavelu","profession":"Legal & Accounting > Legal & Accounting (Other) > Taxation Service","profession_category":"Legal & Accounting","company_name":"Sicher Shared Services Pvt Ltd","city":"Coimbatore,","chapter_id":39146,"region_id":29,"domain":"bni-coimbatore.in"},{"member_id":11335,"full_name":"Keshava Narayan","profession":"Architecture & Engineering > Architect > Architect","profession_category":"Architecture & Engineering","company_name":"Karthigeeta & Associates","city":"Coimbatore","chapter_id":39146,"region_id":29,"domain":"bni-coimbatore.in"},{"member_id":11336,"full_name":"Nikhil Vyaas P.","profession":"Employment Activities > Human Resources > Human Resources","profession_category":"Employment Activities","company_name":"Chanakya HR Management Company","city":"Coimbatore,","chapter_id":39146,"region_id":29,"domain":"bni-coimbatore.in"},{"member_id":11337,"full_name":"Nithin Muthu Alexander M","profession":"Real Estate Services > Real Estate Development > Real Estate Services","profession_category":"Real Estate Services","company_name":"AR Realtors","city":"Coimbatore,","chapter_id":39146,"region_id":29,"domain":"bni-coimbatore.in"},{"member_id":11338,"full_name":"Prabakaran Sundarrajan","profession":"Travel > Travel Agent > Tours & Travel","profession_category":"Travel","company_name":"Pollachi Tours and Travels","city":"Coimbatore,","chapter_id":39146,"region_id":29,"domain":"bni-coimbatore.in"},{"member_id":11339,"full_name":"Prasath Shanmugaraj","profession":"Construction > Windows & Doors > UPVC Windows & Doors","profession_category":"Construction","company_name":"Sri VC Window Solutions","city":"Coimbatore,","chapter_id":39146,"region_id":29,"domain":"bni-coimbatore.in"},{"member_id":11340,"full_name":"Praveen Kumar","profession":"Health & Wellness > Dentist > Dentist","profession_category":"Health & Wellness","company_name":"UNIQ DENTAL CLINIC","city":"Coimbatore,","chapter_id":39146,"region_id":29,"domain":"bni-coimbatore.in"},{"member_id":11341,"full_name":"Princleen Ruban C","profession":"Food & Beverage > Caterer > Caterer","profession_category":"Food & Beverage","company_name":"K Chandran Catering Services","city":"Coimbatore,","chapter_id":39146,"region_id":29,"domain":"bni-coimbatore.in"},{"member_id":11342,"full_name":"Ramki Duraiswamy","profession":"Advertising & Marketing > Photographer > Photographer","profession_category":"Advertising & Marketing","company_name":"YNOT PHOTOGRAPHY","city":"Coimbatore","chapter_id":39146,"region_id":29,"domain":"bni-coimbatore.in"},{"member_id":11343,"full_name":"Rohith Ramu","profession":"Construction > Interior Design - Residential > Interior Design - Residential","profession_category":"Construction","company_name":"Home Square Interiors","city":"Coimbatore","chapter_id":39146,"region_id":29,"domain":"bni-coimbatore.in"},{"member_id":11344,"full_name":"Santhosh L","profession":"Event & Business Service > Events > Events","profession_category":"Event & Business Service","company_name":"Be 2rue Event Managers","city":"Coimbatore, Tamil Nadu","chapter_id":39146,"region_id":29,"domain":"bni-coimbatore.in"},{"member_id":11345,"full_name":"Sathish Kumar","profession":"Car & Motorcycle > Auto/Car Rental/Leasing > Auto/Car Rental/Leasing","profession_category":"Car & Motorcycle","company_name":"Adhu Self Driving Cars","city":"Coimbatore","chapter_id":39146,"region_id":29,"domain":"bni-coimbatore.in"},{"member_id":11346,"full_name":"Savittha S","profession":"Advertising & Marketing > Printer > Printer","profession_category":"Advertising & Marketing","company_name":"Kleur Prints","city":"Coimbatore","chapter_id":39146,"region_id":29,"domain":"bni-coimbatore.in"},{"member_id":11347,"full_name":"Shanmugapriya Veerasamy","profession":"Computer & Programming > Computer & Programming (Other) > Software Development","profession_category":"Computer & Programming","company_name":"ANGA Information Technology Private limited","city":"Coimbatore","chapter_id":39146,"region_id":29,"domain":"bni-coimbatore.in"},{"member_id":11348,"full_name":"Sheeja KV","profession":"Retail > Retail (Other) > Footware (Bata Franchise)","profession_category":"Retail","company_name":"Shara","city":"Coimbatore","chapter_id":39146,"region_id":29,"domain":"bni-coimbatore.in"},{"member_id":11349,"full_name":"Subash Chandran M","profession":"Advertising & Marketing > Digital Marketing > Digital Marketing","profession_category":"Advertising & Marketing","company_name":"JasBells Digital Services","city":"Coimbatore","chapter_id":39146,"region_id":29,"domain":"bni-coimbatore.in"}],"professions":[{"profession_category":"Advertising & Marketing","count":5},{"profession_category":"Retail","count":4},{"profession_category":"Construction","count":3},{"profession_category":"Real Estate Services","count":2},{"profession_category":"Health & Wellness","count":2},{"profession_category":"Travel","count":1},{"profession_category":"Legal & Accounting","count":1},{"profession_category":"Food & Beverage","count":1},{"profession_category":"Finance & Insurance","count":1},{"profession_category":"Event & Business Service","count":1},{"profession_category":"Employment Activities","count":1},{"profession_category":"Computer & Programming","count":1},{"profession_category":"Car & Motorcycle","count":1},{"profession_category":"Architecture & Engineering","count":1}]}