{"chapter":{"chapter_id":9385,"chapter_name":"BNI Legacy","region_id":8,"venue_name":"Davanam Sarovar Portico Suites","address":"Opp Madiwala Police station,, Hosur Main Road,, Bangalore, Karnataka, India, 560068","city":"Opp Madiwala Police station","state":"Karnataka","latitude":12.921019,"longitude":77.6207269,"meeting_day":"Tuesday","meeting_time":"8:00 AM - 9:30 AM","meeting_schedule":"Meets : Every Tuesday, 8:00 AM - 9:30 AM","total_members":25,"domain":"bni-bangalore.in","detail_url":"chapterdetails.php?chapterId=9385&name=BNI+Legacy&t=1f3d9e85188d53166f8236113d796cd7f5db5d46243227ab3de877ee592485c3","org_type":"CHAPTER","region_name":"bangalore"},"members":[{"member_id":2775,"full_name":"Ankitha Goyal","profession":"Construction > Interior Design - Commercial > Interior Design - Commercial","profession_category":"Construction","company_name":"DECON HUB PRIVATE LIMITED","city":"Bengaluru","chapter_id":9385,"region_id":8,"domain":"bni-bangalore.in"},{"member_id":2776,"full_name":"Baladev Mahato","profession":"Food & Beverage > Caterer > Caterer","profession_category":"Food & Beverage","company_name":"HoneyGo Food India Private Limited","city":"Bangalore","chapter_id":9385,"region_id":8,"domain":"bni-bangalore.in"},{"member_id":2777,"full_name":"Chethan Suresh P V","profession":"Construction > Fences > Fences","profession_category":"Construction","company_name":"DEXTRA SQUARE PRIVATE LIMITED","city":"COIMBATORE","chapter_id":9385,"region_id":8,"domain":"bni-bangalore.in"},{"member_id":2778,"full_name":"Devashish  Kumar","profession":"Retail > Gifts > Gifts","profession_category":"Retail","company_name":"UrbanDezine","city":"Bangalore","chapter_id":9385,"region_id":8,"domain":"bni-bangalore.in"},{"member_id":2779,"full_name":"Harshvardhan Sharma","profession":"Legal & Accounting > Lawyer > Lawyer","profession_category":"Legal & Accounting","company_name":"T S SURESH PLUS ASSOCIATES","city":"Bangalore","chapter_id":9385,"region_id":8,"domain":"bni-bangalore.in"},{"member_id":2780,"full_name":"Hemanth Sharma","profession":"Advertising & Marketing > Web Development > Web Development","profession_category":"Advertising & Marketing","company_name":"Spindigo Designs LLP","city":"Bangalore","chapter_id":9385,"region_id":8,"domain":"bni-bangalore.in"},{"member_id":2781,"full_name":"Joe P John","profession":"Training & Coaching > Training & Coaching (Other) > Career Mentor","profession_category":"Training & Coaching","company_name":"Career Mentorz ( Unit of Vantage Ecare Pvt Ltd)","city":"Bangalore","chapter_id":9385,"region_id":8,"domain":"bni-bangalore.in"},{"member_id":2782,"full_name":"Karthikeyan  SJ","profession":"Construction > Electrical Contractor > Electrical Contractor","profession_category":"Construction","company_name":"Ohm Engineering Works","city":"Rajapalayam","chapter_id":9385,"region_id":8,"domain":"bni-bangalore.in"},{"member_id":2783,"full_name":"Lawrence Samuel Raj","profession":"Advertising & Marketing > Photographer > Photographer","profession_category":"Advertising & Marketing","company_name":"Vizdemy Visual Media","city":"Bengaluru","chapter_id":9385,"region_id":8,"domain":"bni-bangalore.in"},{"member_id":2784,"full_name":"Madhusudhan N","profession":"Manufacturing > Furniture manufacture > Furniture manufacture","profession_category":"Manufacturing","company_name":"Desk Square","city":"Bangalore","chapter_id":9385,"region_id":8,"domain":"bni-bangalore.in"},{"member_id":2785,"full_name":"N PRASANNAKUMAR","profession":"Finance & Insurance > Health Insurance > Health Insurance","profession_category":"Finance & Insurance","company_name":"ENSURE INSURE","city":"BANGALORE","chapter_id":9385,"region_id":8,"domain":"bni-bangalore.in"},{"member_id":2786,"full_name":"Nilesh Kumar","profession":"Manufacturing > Manufacturing (Other) > Sweets Manufacturing","profession_category":"Manufacturing","company_name":"KANHALAL INNOVATIVE FOODS PRIVATE LIMITED","city":"Bangalore","chapter_id":9385,"region_id":8,"domain":"bni-bangalore.in"},{"member_id":2787,"full_name":"Pankaj Kumar","profession":"Construction > Builder/General Contractor > Builder/General Contractor","profession_category":"Construction","company_name":"Pathways Constructions","city":"BANGALORE","chapter_id":9385,"region_id":8,"domain":"bni-bangalore.in"},{"member_id":2788,"full_name":"Pratap Mondal","profession":"Finance & Insurance > Consumer Loan > Consumer Loan","profession_category":"Finance & Insurance","company_name":"FINCENTER SERVICE PVT LTD","city":"Bangalore","chapter_id":9385,"region_id":8,"domain":"bni-bangalore.in"},{"member_id":2789,"full_name":"Rajesh Raj","profession":"Retail > Home Theatres > Home Theatres","profession_category":"Retail","company_name":"PROFX TECH LTD","city":"Bangalore","chapter_id":9385,"region_id":8,"domain":"bni-bangalore.in"},{"member_id":2790,"full_name":"Ranjitha Dinesh","profession":"Legal & Accounting > Accounting Services > Accounting Services","profession_category":"Legal & Accounting","company_name":"R D R & Associates","city":"Bangalore","chapter_id":9385,"region_id":8,"domain":"bni-bangalore.in"},{"member_id":2791,"full_name":"Rohakk Shah","profession":"Architecture & Engineering > Architect > Architect","profession_category":"Architecture & Engineering","company_name":"OmnipresenceStudio","city":"Bangalore","chapter_id":9385,"region_id":8,"domain":"bni-bangalore.in"},{"member_id":2792,"full_name":"Ruchi Govil","profession":"Real Estate Services > Real Estate Services (Other) > Real Estate Consultant","profession_category":"Real Estate Services","company_name":"JADE CONSULTANTS","city":"Bangalore","chapter_id":9385,"region_id":8,"domain":"bni-bangalore.in"},{"member_id":2793,"full_name":"Sachin Aggarwal","profession":"Retail > Electrical Equipment > Electrical Equipment","profession_category":"Retail","company_name":"Capital Trading Company","city":"Bangalore","chapter_id":9385,"region_id":8,"domain":"bni-bangalore.in"},{"member_id":2794,"full_name":"Sai Yaswanth  Kathi","profession":"Manufacturing > Packaging > Packaging","profession_category":"Manufacturing","company_name":"Eco Handles","city":"Bangalore","chapter_id":9385,"region_id":8,"domain":"bni-bangalore.in"},{"member_id":2795,"full_name":"Someshwara L.R","profession":"Finance & Insurance > Finance & Insurance (Other) > Chit Funds","profession_category":"Finance & Insurance","company_name":"Vasavi Khannika Chits Pvt Ltd","city":"Bangalore","chapter_id":9385,"region_id":8,"domain":"bni-bangalore.in"},{"member_id":2796,"full_name":"Subramanian  Jayaraman","profession":"Finance & Insurance > Financial Advisor > Financial Advisor","profession_category":"Finance & Insurance","company_name":"Ultimate Management Solutions Private Limited","city":"Bangalore","chapter_id":9385,"region_id":8,"domain":"bni-bangalore.in"},{"member_id":2797,"full_name":"Suresh Muthuswamy","profession":"Employment Activities > Recruiter > Recruiter","profession_category":"Employment Activities","company_name":"Axycube Solutions Private Limited","city":"Bengaluru","chapter_id":9385,"region_id":8,"domain":"bni-bangalore.in"},{"member_id":2798,"full_name":"Vishal Tak","profession":"Construction > Flooring > Flooring","profession_category":"Construction","company_name":"S M Rocks& Stones Pvt Ltd","city":"Bangalore","chapter_id":9385,"region_id":8,"domain":"bni-bangalore.in"},{"member_id":2799,"full_name":"Vrishaab V","profession":"Advertising & Marketing > Digital Marketing > Digital Marketing","profession_category":"Advertising & Marketing","company_name":"Brand Crest Digital","city":"Bengaluru","chapter_id":9385,"region_id":8,"domain":"bni-bangalore.in"}],"professions":[{"profession_category":"Construction","count":5},{"profession_category":"Finance & Insurance","count":4},{"profession_category":"Retail","count":3},{"profession_category":"Manufacturing","count":3},{"profession_category":"Advertising & Marketing","count":3},{"profession_category":"Legal & Accounting","count":2},{"profession_category":"Training & Coaching","count":1},{"profession_category":"Real Estate Services","count":1},{"profession_category":"Food & Beverage","count":1},{"profession_category":"Employment Activities","count":1},{"profession_category":"Architecture & Engineering","count":1}]}